<annotation>
	<folder>33</folder>
	<filename>33175.JPG</filename>
	<path>/Users/cristianrosales/Desktop/TrabajoTerminal/VinosCyT/33/33175.JPG</path>
	<source>
		<database>Unknown</database>
	</source>
	<size>
		<width>300</width>
		<height>400</height>
		<depth>3</depth>
	</size>
	<segmented>0</segmented>
	<object>
		<name>reservado sweet red</name>
		<pose>Unspecified</pose>
		<truncated>0</truncated>
		<difficult>0</difficult>
		<bndbox>
			<xmin>84</xmin>
			<ymin>4</ymin>
			<xmax>202</xmax>
			<ymax>357</ymax>
		</bndbox>
	</object>
</annotation>
