<annotation>
	<folder>2</folder>
	<filename>2076.JPG</filename>
	<path>/Users/cristianrosales/Desktop/TrabajoTerminal/VinosCyT/2/2076.JPG</path>
	<source>
		<database>Unknown</database>
	</source>
	<size>
		<width>300</width>
		<height>400</height>
		<depth>3</depth>
	</size>
	<segmented>0</segmented>
	<object>
		<name>reservado merlot</name>
		<pose>Unspecified</pose>
		<truncated>0</truncated>
		<difficult>0</difficult>
		<bndbox>
			<xmin>48</xmin>
			<ymin>14</ymin>
			<xmax>272</xmax>
			<ymax>392</ymax>
		</bndbox>
	</object>
</annotation>
